midom/__init__.py
midom/components.py
midom/constants.py
midom/identifiers.py
midom/subspaces.py
midom/validation.py
midom-0.4.0.dist-info/licenses/LICENSE
midom-0.4.0.dist-info/METADATA
midom-0.4.0.dist-info/WHEEL
midom-0.4.0.dist-info/top_level.txt
midom-0.4.0.dist-info/RECORD
