Metadata-Version: 2.4
Name: midom
Version: 0.4.0
Summary: Concepts and relations to describe the process of DICOM deidentification
License-Expression: AGPL-3.0-or-later
Classifier: Development Status :: 4 - Beta
Classifier: Intended Audience :: Developers
Classifier: Programming Language :: Python :: 3.12
Classifier: Programming Language :: Python :: 3.13
Requires-Python: >=3.12
License-File: LICENSE
Requires-Dist: dicomcriterion>=0.1.0
Requires-Dist: pydantic>=2.11.5
Requires-Dist: pydicom>=2.4.4
Requires-Dist: sphinx>=7.4.7
Requires-Dist: sphinx-rtd-theme>=3.0.2
Requires-Dist: sphinxcontrib-plantuml>=0.30
Dynamic: license-file
